easy_communication/__init__.py
easy_communication-0.0.1.dist-info/METADATA
easy_communication-0.0.1.dist-info/WHEEL
easy_communication-0.0.1.dist-info/top_level.txt
easy_communication-0.0.1.dist-info/RECORD
