Metadata-Version: 2.1
Name: easy-communication
Version: 0.0.1
Summary: A simple communication between processes
Home-page: https://github.com/develask/easy_communication
Author: Mikel de Velasco
Author-email: develascomikel@gmail.com
License: UNKNOWN
Platform: UNKNOWN
Classifier: Programming Language :: Python :: 3
Classifier: License :: OSI Approved :: MIT License
Classifier: Operating System :: OS Independent
Requires-Python: >=3.6
